.DS_Store
frankenpoem/__init__.py
frankenpoem/data.pkl.compress
frankenpoem-7.0.0.dist-info/LICENSE
frankenpoem-7.0.0.dist-info/METADATA
frankenpoem-7.0.0.dist-info/WHEEL
frankenpoem-7.0.0.dist-info/top_level.txt
frankenpoem-7.0.0.dist-info/RECORD
